pytextforge/__init__.py
pytextforge/__main__.py
pytextforge/file.py
pytextforge/forge.py
pytextforge/inputs.py
pytextforge/messages.py
pytextforge/metadata.py
pytextforge-1.0.2.dist-info/METADATA
pytextforge-1.0.2.dist-info/WHEEL
pytextforge-1.0.2.dist-info/entry_points.txt
pytextforge-1.0.2.dist-info/top_level.txt
pytextforge-1.0.2.dist-info/RECORD
