Metadata-Version: 2.1
Name: pytextforge
Version: 1.0.2
Summary: One module to generate files from a template
Home-page: https://github.com/RobertoRojas/PyTextForge
Author: Rojas, Roberto
License: UNKNOWN
Platform: UNKNOWN
Classifier: Programming Language :: Python :: 3
Classifier: License :: OSI Approved :: Apache Software License
Classifier: Operating System :: OS Independent
Requires-Python: >=3.6
Requires-Dist: Jinja2 (==3.1.2)
Requires-Dist: MarkupSafe (==2.1.3)
Requires-Dist: colorama (==0.4.6)
